lazurite/__init__.py
lazurite/__main__.py
lazurite/cli.py
lazurite/tempfile.py
lazurite/util.py
lazurite/compiler/__init__.py
lazurite/compiler/dxc.py
lazurite/compiler/glslang.py
lazurite/compiler/macro_define.py
lazurite/compiler/shaderc.py
lazurite/decompiler/__init__.py
lazurite/decompiler/varying_decompiler.py
lazurite/decompiler/macro_decompiler/__init__.py
lazurite/decompiler/macro_decompiler/all_flags.py
lazurite/decompiler/macro_decompiler/diffing.py
lazurite/decompiler/macro_decompiler/encoded_shader.py
lazurite/decompiler/macro_decompiler/expression_processing.py
lazurite/decompiler/macro_decompiler/expression_search.py
lazurite/decompiler/macro_decompiler/grouped_shader.py
lazurite/decompiler/macro_decompiler/local_flag_definition.py
lazurite/decompiler/macro_decompiler/macro_decompiler.py
lazurite/decompiler/macro_decompiler/permutation.py
lazurite/decompiler/macro_decompiler/processing.py
lazurite/decompiler/macro_decompiler/type_aliases.py
lazurite/material/__init__.py
lazurite/material/buffer.py
lazurite/material/encryption.py
lazurite/material/material.py
lazurite/material/platform.py
lazurite/material/precision.py
lazurite/material/stage.py
lazurite/material/uniform.py
lazurite/material/shader_pass/__init__.py
lazurite/material/shader_pass/bgfx_shader.py
lazurite/material/shader_pass/blend_mode.py
lazurite/material/shader_pass/shader_definition.py
lazurite/material/shader_pass/shader_input.py
lazurite/material/shader_pass/shader_pass.py
lazurite/material/shader_pass/supported_platforms.py
lazurite/material/shader_pass/variant.py
lazurite/project/__init__.py
lazurite/project/compiler_type.py
lazurite/project/material_config.py
lazurite/project/project.py
lazurite/project/project_config.py
lazurite/project/shader_file_overwrite.py
lazurite-0.7.0.dist-info/licenses/LICENSE
lazurite-0.7.0.dist-info/METADATA
lazurite-0.7.0.dist-info/WHEEL
lazurite-0.7.0.dist-info/entry_points.txt
lazurite-0.7.0.dist-info/top_level.txt
lazurite-0.7.0.dist-info/RECORD
